ardhi_framework/__init__.py
ardhi_framework/application.py
ardhi_framework/apps.py
ardhi_framework/authentication.py
ardhi_framework/checks.py
ardhi_framework/compatibility.py
ardhi_framework/decorators.py
ardhi_framework/default_views.py
ardhi_framework/dispatch.py
ardhi_framework/documentation.py
ardhi_framework/events.py
ardhi_framework/exceptions.py
ardhi_framework/fields.py
ardhi_framework/generics.py
ardhi_framework/interservice.py
ardhi_framework/middleware.py
ardhi_framework/mixins.py
ardhi_framework/models.py
ardhi_framework/request.py
ardhi_framework/response.py
ardhi_framework/routers.py
ardhi_framework/serializers.py
ardhi_framework/status.py
ardhi_framework/utils.py
ardhi_framework/validators.py
ardhi_framework/views.py
ardhi_framework/definitions/__init__.py
ardhi_framework/definitions/exceptions.py
ardhi_framework/definitions/ownership.py
ardhi_framework/management/__init__.py
ardhi_framework/management/commands/__init__.py
ardhi_framework/management/commands/addprocess.py
ardhi_framework/mfa/__init__.py
ardhi_framework/mfa/base_mfa.py
ardhi_framework/mfa/fingerprint.py
ardhi_framework/mfa/otps.py
ardhi_framework/mfa/signatures.py
ardhi_framework/migrations/0001_initial.py
ardhi_framework/migrations/0002_remove_departmentparcelregistrymodel_fz_and_more.py
ardhi_framework/migrations/__init__.py
ardhi_framework/permissions/__init__.py
ardhi_framework/permissions/base_permissions.py
ardhi_framework/permissions/land_registration.py
ardhi_framework/permissions/land_survey.py
ardhi_framework/property_ownership/__init__.py
ardhi_framework/property_ownership/audit_ownership.py
ardhi_framework/property_ownership/complex_formatter.py
ardhi_framework/property_ownership/ownership_base_util.py
ardhi_framework/property_ownership/refactor_ownership.py
ardhi_framework/property_ownership/serializers.py
ardhi_framework/property_processing/__init__.py
ardhi_framework/property_processing/snitch.py
ardhi_framework/property_processing/transactibility_validator.py
ardhi_framework-0.1.6.dist-info/licenses/LICENSE
ardhi_framework-0.1.6.dist-info/METADATA
ardhi_framework-0.1.6.dist-info/WHEEL
ardhi_framework-0.1.6.dist-info/top_level.txt
ardhi_framework-0.1.6.dist-info/RECORD
