Metadata-Version: 2.4
Name: ardhi_framework
Version: 0.1.6
Summary: Ardhi Framework for land transactions.
Home-page: https://www.ardhisasa.go.ke/
Author: Vincent Kioko
Author-email: kiokovincent12@gmail.com
License: MIT
Project-URL: Funding, https://wearefreeopen/
Project-URL: Source, https://gitlab.com/ardhisasa/ardhi-framework
Project-URL: Changelog, https://no-changelog-yet.com
Classifier: Development Status :: 5 - Production/Stable
Classifier: Environment :: Web Environment
Classifier: Framework :: Django
Classifier: Framework :: Django :: 4.2
Classifier: Framework :: Django :: 5.0
Classifier: Framework :: Django :: 5.1
Classifier: Framework :: Django :: 5.2
Classifier: Intended Audience :: Developers
Classifier: Operating System :: OS Independent
Classifier: Programming Language :: Python
Classifier: Programming Language :: Python :: 3
Classifier: Programming Language :: Python :: 3.9
Classifier: Programming Language :: Python :: 3.10
Classifier: Programming Language :: Python :: 3.11
Classifier: Programming Language :: Python :: 3.12
Classifier: Programming Language :: Python :: 3.13
Classifier: Programming Language :: Python :: 3 :: Only
Classifier: Topic :: Internet :: WWW/HTTP
Requires-Python: >=3.9
License-File: LICENSE
Requires-Dist: django>=3.2
Requires-Dist: djangorestframework>=3.0
Requires-Dist: PyJWT
Dynamic: author
Dynamic: author-email
Dynamic: classifier
Dynamic: description
Dynamic: description-content-type
Dynamic: home-page
Dynamic: license
Dynamic: license-file
Dynamic: project-url
Dynamic: requires-dist
Dynamic: requires-python
Dynamic: summary
